geler/__init__.py
geler/__main__.py
geler_certic-0.4.5.dist-info/METADATA
geler_certic-0.4.5.dist-info/WHEEL
geler_certic-0.4.5.dist-info/entry_points.txt
geler_certic-0.4.5.dist-info/licenses/LICENSE.txt
geler_certic-0.4.5.dist-info/RECORD
