Metadata-Version: 2.4
Name: geler-CERTIC
Version: 0.4.5
Summary: Help convert dynamic webistes to static ones.
Author-email: Mickaël Desfrênes <mickael.desfrenes@unicaen.fr>
Maintainer-email: Mickaël Desfrênes <mickael.desfrenes@unicaen.fr>
License: CECILL-C
License-File: LICENSE.txt
Requires-Python: <4.0,>=3.9
Requires-Dist: argh>=0.31.3
Requires-Dist: beautifulsoup4>=4.12.3
Requires-Dist: cssutils>=2.11.1
Requires-Dist: requests>=2.32.3
